{
  "data": [
    {
      "date": "2020-11-01",
      "overnight": 1453.44,
      "1_week": null,
      "1_month": null,
      "3_month": null,
      "6_month": null,
      "1_year": null,
      "other": null
    },
    {
      "date": "2020-11-02",
      "overnight": 2085.61,
      "1_week": 400,
      "1_month": 50,
      "3_month": null,
      "6_month": null,
      "1_year": null,
      "other": 100
    },
    {
      "date": "2020-11-03",
      "overnight": 2503.06,
      "1_week": null,
      "1_month": null,
      "3_month": null,
      "6_month": null,
      "1_year": null,
      "other": 100
    },
    {
      "date": "2020-11-04",
      "overnight": 1098.58,
      "1_week": 650,
      "1_month": 700,
      "3_month": null,
      "6_month": null,
      "1_year": null,
      "other": 860
    },
    {
      "date": "2020-11-05",
      "overnight": 1904.87,
      "1_week": 300,
      "1_month": 900,
      "3_month": null,
      "6_month": null,
      "1_year": null,
      "other": 1050
    },
    {
      "date": "2020-11-06",
      "overnight": 2413.08,
      "1_week": 200,
      "1_month": 130,
      "3_month": null,
      "6_month": null,
      "1_year": null,
      "other": 1150
    },
    {
      "date": "2020-11-07",
      "overnight": 2413.08,
      "1_week": 200,
      "1_month": 130,
      "3_month": null,
      "6_month": null,
      "1_year": null,
      "other": 1150
    },
    {
      "date": "2020-11-08",
      "overnight": 2413.08,
      "1_week": 200,
      "1_month": 130,
      "3_month": null,
      "6_month": null,
      "1_year": null,
      "other": 1150
    },
    {
      "date": "2020-11-09",
      "overnight": 1649.56,
      "1_week": null,
      "1_month": null,
      "3_month": null,
      "6_month": null,
      "1_year": null,
      "other": 100
    },
    {
      "date": "2020-11-10",
      "overnight": 2775.89,
      "1_week": 50,
      "1_month": null,
      "3_month": null,
      "6_month": null,
      "1_year": null,
      "other": 690
    },
    {
      "date": "2020-11-11",
      "overnight": 3473.26,
      "1_week": 120,
      "1_month": null,
      "3_month": null,
      "6_month": null,
      "1_year": null,
      "other": 840
    },
    {
      "date": "2020-11-12",
      "overnight": 5125.89,
      "1_week": null,
      "1_month": null,
      "3_month": null,
      "6_month": null,
      "1_year": null,
      "other": null
    },
    {
      "date": "2020-11-13",
      "overnight": 3926.05,
      "1_week": 500,
      "1_month": null,
      "3_month": null,
      "6_month": null,
      "1_year": null,
      "other": 395
    },
    {
      "date": "2020-11-14",
      "overnight": 3926.05,
      "1_week": 500,
      "1_month": null,
      "3_month": null,
      "6_month": null,
      "1_year": null,
      "other": 395
    },
    {
      "date": "2020-11-15",
      "overnight": 3926.05,
      "1_week": 500,
      "1_month": null,
      "3_month": null,
      "6_month": null,
      "1_year": null,
      "other": 395
    },
    {
      "date": "2020-11-16",
      "overnight": 1949.47,
      "1_week": 750,
      "1_month": 405,
      "3_month": null,
      "6_month": null,
      "1_year": null,
      "other": 50
    },
    {
      "date": "2020-11-17",
      "overnight": 2619.06,
      "1_week": null,
      "1_month": null,
      "3_month": null,
      "6_month": null,
      "1_year": null,
      "other": 250
    },
    {
      "date": "2020-11-18",
      "overnight": 2613.61,
      "1_week": 220,
      "1_month": null,
      "3_month": null,
      "6_month": null,
      "1_year": null,
      "other": 200
    },
    {
      "date": "2020-11-19",
      "overnight": 1613.57,
      "1_week": null,
      "1_month": null,
      "3_month": 100,
      "6_month": null,
      "1_year": null,
      "other": 440
    },
    {
      "date": "2020-11-20",
      "overnight": 2035.87,
      "1_week": 300,
      "1_month": null,
      "3_month": null,
      "6_month": null,
      "1_year": null,
      "other": 1110
    },
    {
      "date": "2020-11-21",
      "overnight": 2035.87,
      "1_week": 300,
      "1_month": null,
      "3_month": null,
      "6_month": null,
      "1_year": null,
      "other": 1110
    },
    {
      "date": "2020-11-22",
      "overnight": 2035.87,
      "1_week": 300,
      "1_month": null,
      "3_month": null,
      "6_month": null,
      "1_year": null,
      "other": 1110
    },
    {
      "date": "2020-11-23",
      "overnight": 3591.46,
      "1_week": 200,
      "1_month": 100,
      "3_month": null,
      "6_month": null,
      "1_year": null,
      "other": null
    },
    {
      "date": "2020-11-24",
      "overnight": 3024.76,
      "1_week": null,
      "1_month": null,
      "3_month": null,
      "6_month": null,
      "1_year": null,
      "other": null
    },
    {
      "date": "2020-11-25",
      "overnight": 3809.24,
      "1_week": 110,
      "1_month": null,
      "3_month": null,
      "6_month": null,
      "1_year": null,
      "other": 400
    },
    {
      "date": "2020-11-26",
      "overnight": 3469.54,
      "1_week": null,
      "1_month": null,
      "3_month": null,
      "6_month": null,
      "1_year": null,
      "other": 110
    },
    {
      "date": "2020-11-27",
      "overnight": 2734.03,
      "1_week": null,
      "1_month": 220,
      "3_month": null,
      "6_month": null,
      "1_year": null,
      "other": 50
    },
    {
      "date": "2020-11-28",
      "overnight": 2734.03,
      "1_week": null,
      "1_month": 220,
      "3_month": null,
      "6_month": null,
      "1_year": null,
      "other": 50
    },
    {
      "date": "2020-11-29",
      "overnight": 2734.03,
      "1_week": null,
      "1_month": 220,
      "3_month": null,
      "6_month": null,
      "1_year": null,
      "other": 50
    },
    {
      "date": "2020-11-30",
      "overnight": 2525.05,
      "1_week": null,
      "1_month": null,
      "3_month": null,
      "6_month": null,
      "1_year": null,
      "other": 300
    }
  ],
  "meta": {
    "product": "interbank",
    "last_updated": "2025-08-22 23:01:24",
    "total_result": 0
  }
}