{
  "data": [
    {
      "reference_date": "2025-06-03",
      "reference_rate": "3.00",
      "aggregate_volume": "27788.82"
    },
    {
      "reference_date": "2025-06-04",
      "reference_rate": "3.00",
      "aggregate_volume": "28480.81"
    },
    {
      "reference_date": "2025-06-05",
      "reference_rate": "3.00",
      "aggregate_volume": "26518.56"
    },
    {
      "reference_date": "2025-06-06",
      "reference_rate": "3.00",
      "aggregate_volume": "26671.30"
    },
    {
      "reference_date": "2025-06-09",
      "reference_rate": "3.00",
      "aggregate_volume": "27459.35"
    },
    {
      "reference_date": "2025-06-10",
      "reference_rate": "3.00",
      "aggregate_volume": "30203.85"
    },
    {
      "reference_date": "2025-06-11",
      "reference_rate": "3.00",
      "aggregate_volume": "29736.51"
    },
    {
      "reference_date": "2025-06-12",
      "reference_rate": "3.00",
      "aggregate_volume": "30097.95"
    },
    {
      "reference_date": "2025-06-13",
      "reference_rate": "3.00",
      "aggregate_volume": "27477.31"
    },
    {
      "reference_date": "2025-06-16",
      "reference_rate": "3.00",
      "aggregate_volume": "24661.99"
    },
    {
      "reference_date": "2025-06-17",
      "reference_rate": "3.00",
      "aggregate_volume": "26911.89"
    },
    {
      "reference_date": "2025-06-18",
      "reference_rate": "3.00",
      "aggregate_volume": "25771.32"
    },
    {
      "reference_date": "2025-06-19",
      "reference_rate": "3.00",
      "aggregate_volume": "21473.23"
    },
    {
      "reference_date": "2025-06-20",
      "reference_rate": "3.00",
      "aggregate_volume": "23841.44"
    },
    {
      "reference_date": "2025-06-23",
      "reference_rate": "3.00",
      "aggregate_volume": "27065.35"
    },
    {
      "reference_date": "2025-06-24",
      "reference_rate": "3.00",
      "aggregate_volume": "25028.54"
    },
    {
      "reference_date": "2025-06-25",
      "reference_rate": "3.00",
      "aggregate_volume": "26172.42"
    },
    {
      "reference_date": "2025-06-26",
      "reference_rate": "3.00",
      "aggregate_volume": "23349.05"
    },
    {
      "reference_date": "2025-06-30",
      "reference_rate": "3.00",
      "aggregate_volume": "26932.01"
    }
  ],
  "meta": {
    "last_updated": "2025-08-22 11:01:06",
    "total_result": 19
  }
}